{"_invocation_id": "0658835e-f03c-4f4d-bee4-283bd9ae7f0d", "linked": {"0": {"name": "model.medical_warehouse.fct_messages", "type": "model", "succ": [3, 4, 11]}, "1": {"name": "model.medical_warehouse.stg_telegram_messages", "type": "model", "succ": [0, 2, 7, 8, 9, 10]}, "2": {"name": "model.medical_warehouse.dim_channels", "type": "model", "succ": [5, 6]}, "3": {"name": "test.medical_warehouse.not_null_fct_messages_message_id.de346706b5", "type": "test"}, "4": {"name": "test.medical_warehouse.not_null_fct_messages_channel_name.baf21c28de", "type": "test"}, "5": {"name": "test.medical_warehouse.not_null_dim_channels_channel_name.3be3fa8f5b", "type": "test"}, "6": {"name": "test.medical_warehouse.unique_dim_channels_channel_name.e57614abc8", "type": "test"}, "7": {"name": "test.medical_warehouse.not_null_stg_telegram_messages_message_id.9b3fea71d6", "type": "test"}, "8": {"name": "test.medical_warehouse.not_null_stg_telegram_messages_channel_name.38886ae8d8", "type": "test"}, "9": {"name": "test.medical_warehouse.not_null_stg_telegram_messages_views.433c12e936", "type": "test"}, "10": {"name": "model.medical_warehouse.dim_dates", "type": "model"}, "11": {"name": "test.medical_warehouse.assert_positive_views", "type": "test"}}}